{
    "total": [
        {
            "id": "61554221352772",
            "count": 0
        },
        {
            "id": "100075302427263",
            "count": 0
        },
        {
            "id": "100084035917282",
            "count": 9
        },
        {
            "id": "100088577864287",
            "count": 0
        },
        {
            "id": "100089281770842",
            "count": 65
        },
        {
            "id": "61562779757407",
            "count": 0
        },
        {
            "id": "61557543538603",
            "count": 0
        },
        {
            "id": "100080759211177",
            "count": 1
        },
        {
            "id": "100038740121428",
            "count": 3
        },
        {
            "id": "61562261835048",
            "count": 2
        },
        {
            "id": "61550962658401",
            "count": 26
        },
        {
            "id": "100072439105441",
            "count": 12
        },
        {
            "id": "61563477320639",
            "count": 0
        },
        {
            "id": "61563450811249",
            "count": 76
        },
        {
            "id": "100046194132744",
            "count": 59
        },
        {
            "id": "100000264111892",
            "count": 76
        },
        {
            "id": "61560076791853",
            "count": 0
        },
        {
            "id": "100090073282948",
            "count": 2
        },
        {
            "id": "61563370010550",
            "count": 102
        },
        {
            "id": "100083174347639",
            "count": 45
        },
        {
            "id": "100094911711160",
            "count": 15
        },
        {
            "id": "100073420669646",
            "count": 51
        },
        {
            "id": "100009801367183",
            "count": 21
        },
        {
            "id": "61553578030636",
            "count": 99
        },
        {
            "id": "61552707897116",
            "count": 129
        },
        {
            "id": "61561840845811",
            "count": 0
        },
        {
            "id": "61560667599787",
            "count": 2
        },
        {
            "id": "61560179044114",
            "count": 17
        },
        {
            "id": "61563440668643",
            "count": 167
        },
        {
            "id": "61558691518366",
            "count": 0
        },
        {
            "id": "100089033040313",
            "count": 4
        },
        {
            "id": "61562501226870",
            "count": 10
        },
        {
            "id": "61553643156660",
            "count": 72
        },
        {
            "id": "61562870807559",
            "count": 16
        },
        {
            "id": "100081016996783",
            "count": 63
        },
        {
            "id": "61561992007088",
            "count": 0
        },
        {
            "id": "100085073240621",
            "count": 24
        },
        {
            "id": "61556666968083",
            "count": 370
        },
        {
            "id": "61561362279600",
            "count": 22
        },
        {
            "id": "61553948224884",
            "count": 94
        },
        {
            "id": "100035234417533",
            "count": 108
        },
        {
            "id": "100003133525251",
            "count": 53
        },
        {
            "id": "61563600270027",
            "count": 3
        },
        {
            "id": "61563195821713",
            "count": 7
        },
        {
            "id": "61563510337368",
            "count": 58
        },
        {
            "id": "100055304494389",
            "count": 0
        },
        {
            "id": "61563549853253",
            "count": 7
        },
        {
            "id": "61560261936624",
            "count": 8
        }
    ],
    "week": [
        {
            "id": "61554221352772",
            "count": 0,
            "name": "Hoàng Thiên"
        },
        {
            "id": "100075302427263",
            "count": 0,
            "name": "Nguyen Huyen My"
        },
        {
            "id": "100084035917282",
            "count": 0,
            "name": "Ken Yeuem"
        },
        {
            "id": "100088577864287",
            "count": 0,
            "name": "Như Quỳnh"
        },
        {
            "id": "100089281770842",
            "count": 1,
            "name": "Dương Như"
        },
        {
            "id": "61562779757407",
            "count": 0,
            "name": "Người dùng Facebook"
        },
        {
            "id": "61557543538603",
            "count": 0,
            "name": "Người dùng Facebook"
        },
        {
            "id": "100080759211177",
            "count": 0,
            "name": "Bright Dzai"
        },
        {
            "id": "100038740121428",
            "count": 1,
            "name": "Duy メ"
        },
        {
            "id": "61562261835048",
            "count": 0,
            "name": "Cá Chà Bặc"
        },
        {
            "id": "61550962658401",
            "count": 1,
            "name": "Lê Ngọc Khánh Băng"
        },
        {
            "id": "100072439105441",
            "count": 0,
            "name": "Lê Chí"
        },
        {
            "id": "61563477320639",
            "count": 0,
            "name": "Người dùng Facebook"
        },
        {
            "id": "61563450811249",
            "count": 0,
            "name": "Facebook user"
        },
        {
            "id": "100046194132744",
            "count": 1,
            "name": "Đặng Thị Hồng Hải"
        },
        {
            "id": "100000264111892",
            "count": 0,
            "name": "Trịnh Duy Toàn 🖕🏻🐕🐈"
        },
        {
            "id": "61560076791853",
            "count": 0,
            "name": "Nguyễn Quang Trí"
        },
        {
            "id": "100090073282948",
            "count": 0,
            "name": "Gia Long"
        },
        {
            "id": "61563370010550",
            "count": 0,
            "name": "࿐ www.defloration.biz ꗈ Có Lẽ Anh Đã Quá Yêu Em ツ Và Rồi Nhận Ra ღ Em Mang Cho Ta Những Đắng Cay Và Có Lẽ Anh Đã Quá Thương Em ꗈ Giờ Còn Hư Vô 噩 Anh Muốn Vùi Chôn Bao Tháng Ngày ༈፨ Em Đã Xa Anh 噩 Vào Trong Một Chiều Mưa Bay Mang Những Yêu Thương Hòa Du Câu Ca Với Mây Quên Hết Đi Bao Ngày ༈፨ Còn Đọng Lại Trong Nơi Tim ღ Anh Biết Những Chân Thành ಠ༅ཹ﴾ Sẽ Không Dành Cho Anh ꗈ www.drporntube.com ࿐"
        },
        {
            "id": "100083174347639",
            "count": 0,
            "name": "Nguyễn Đức Bình✅"
        },
        {
            "id": "100094911711160",
            "count": 4,
            "name": "Ng Viet Hoang"
        },
        {
            "id": "100073420669646",
            "count": 0,
            "name": "Trần Ngọc Phương Linh"
        },
        {
            "id": "100009801367183",
            "count": 0,
            "name": "Quyết Hoàng"
        },
        {
            "id": "61553578030636",
            "count": 3,
            "name": "Nguyễn Trãi"
        },
        {
            "id": "61552707897116",
            "count": 0,
            "name": "ޑޫއޮންގް ތައި ސަންގް އެވެ"
        },
        {
            "id": "61561840845811",
            "count": 0,
            "name": "Người dùng Facebook"
        },
        {
            "id": "61560667599787",
            "count": 2,
            "name": "Hạ Dương"
        },
        {
            "id": "61560179044114",
            "count": 0,
            "name": "Ngọc Nhi"
        },
        {
            "id": "61563440668643",
            "count": 0,
            "name": "Trần Tú"
        },
        {
            "id": "61558691518366",
            "count": 0,
            "name": "Người dùng Facebook"
        },
        {
            "id": "100089033040313",
            "count": 0,
            "name": "Nguyễn Đức Toàn"
        },
        {
            "id": "61562501226870",
            "count": 0,
            "name": "Ngọc Nhi"
        },
        {
            "id": "61553643156660",
            "count": 0,
            "name": "Nguyễn Hoàng"
        },
        {
            "id": "61562870807559",
            "count": 0,
            "name": "Thai Sang"
        },
        {
            "id": "100081016996783",
            "count": 0,
            "name": "Phng Nhi"
        },
        {
            "id": "61561992007088",
            "count": 0,
            "name": "Ngu Ngu Ngu Ngu"
        },
        {
            "id": "100085073240621",
            "count": 0,
            "name": "Dang Gia Khanh"
        },
        {
            "id": "61556666968083",
            "count": 2,
            "name": "Bố Là Gkhanh"
        },
        {
            "id": "61561362279600",
            "count": 0,
            "name": "Rozjx Virky"
        },
        {
            "id": "61553948224884",
            "count": 0,
            "name": "Duck no sad"
        },
        {
            "id": "100035234417533",
            "count": 0,
            "name": "NGUYỄN HỮU ĐỨC"
        },
        {
            "id": "100003133525251",
            "count": 0,
            "name": "Anh Cte Nhất Meta"
        },
        {
            "id": "61563600270027",
            "count": 0,
            "name": "aaaaaaaaaaaaaaaaaaaaaaaaaaaaaaaaaaaaaaaaaaaaaaaaaaaaaaaaaaaaaaaaaaaaaaaaaaa"
        },
        {
            "id": "61563195821713",
            "count": 0,
            "name": "j"
        },
        {
            "id": "61563510337368",
            "count": 0,
            "name": "Xin Chào Bot"
        },
        {
            "id": "100055304494389",
            "count": 0,
            "name": "ফেইটান পৰ্টৰ"
        },
        {
            "id": "61563549853253",
            "count": 0,
            "name": "Thu Dũng"
        },
        {
            "id": "61560261936624",
            "count": 6,
            "name": "Nguyễn Nam"
        }
    ],
    "day": [
        {
            "id": "61554221352772",
            "count": 0,
            "name": "Hoàng Thiên"
        },
        {
            "id": "100075302427263",
            "count": 0,
            "name": "Nguyen Huyen My"
        },
        {
            "id": "100084035917282",
            "count": 0,
            "name": "Ken Yeuem"
        },
        {
            "id": "100088577864287",
            "count": 0,
            "name": "Như Quỳnh"
        },
        {
            "id": "100089281770842",
            "count": 0,
            "name": "Dương Như"
        },
        {
            "id": "61562779757407",
            "count": 0,
            "name": "Người dùng Facebook"
        },
        {
            "id": "61557543538603",
            "count": 0,
            "name": "Người dùng Facebook"
        },
        {
            "id": "100080759211177",
            "count": 0,
            "name": "Bright Dzai"
        },
        {
            "id": "100038740121428",
            "count": 0,
            "name": "Duy メ"
        },
        {
            "id": "61562261835048",
            "count": 0,
            "name": "Người dùng Facebook"
        },
        {
            "id": "61550962658401",
            "count": 0,
            "name": "Lê Ngọc Khánh Băng"
        },
        {
            "id": "100072439105441",
            "count": 0,
            "name": "Lê Chí"
        },
        {
            "id": "61563477320639",
            "count": 0,
            "name": "Người dùng Facebook"
        },
        {
            "id": "61563450811249",
            "count": 0,
            "name": "Người dùng Facebook"
        },
        {
            "id": "100046194132744",
            "count": 0,
            "name": "Đặng Thị Hồng Hải"
        },
        {
            "id": "100000264111892",
            "count": 0,
            "name": "Trịnh Duy Toàn 🖕🏻🐕🐈"
        },
        {
            "id": "61560076791853",
            "count": 0,
            "name": "Người dùng Facebook"
        },
        {
            "id": "100090073282948",
            "count": 0,
            "name": "Gia Long"
        },
        {
            "id": "61563370010550",
            "count": 0,
            "name": "࿐ www.defloration.biz ꗈ Có Lẽ Anh Đã Quá Yêu Em ツ Và Rồi Nhận Ra ღ Em Mang Cho Ta Những Đắng Cay Và Có Lẽ Anh Đã Quá Thương Em ꗈ Giờ Còn Hư Vô 噩 Anh Muốn Vùi Chôn Bao Tháng Ngày ༈፨ Em Đã Xa Anh 噩 Vào Trong Một Chiều Mưa Bay Mang Những Yêu Thương Hòa Du Câu Ca Với Mây Quên Hết Đi Bao Ngày ༈፨ Còn Đọng Lại Trong Nơi Tim ღ Anh Biết Những Chân Thành ಠ༅ཹ﴾ Sẽ Không Dành Cho Anh ꗈ www.drporntube.com ࿐"
        },
        {
            "id": "100083174347639",
            "count": 0,
            "name": "Nguyễn Đức Bình✅"
        },
        {
            "id": "100094911711160",
            "count": 0,
            "name": "Ng Viet Hoang"
        },
        {
            "id": "100073420669646",
            "count": 0,
            "name": "Trần Ngọc Phương Linh"
        },
        {
            "id": "100009801367183",
            "count": 0,
            "name": "Quyết Hoàng"
        },
        {
            "id": "61553578030636",
            "count": 1,
            "name": "Nguyễn Trãi"
        },
        {
            "id": "61552707897116",
            "count": 0,
            "name": "ޑޫއޮންގް ތައި ސަންގް އެވެ"
        },
        {
            "id": "61561840845811",
            "count": 0,
            "name": "Người dùng Facebook"
        },
        {
            "id": "61560667599787",
            "count": 0,
            "name": "Hạ Dương"
        },
        {
            "id": "61560179044114",
            "count": 0,
            "name": "Ngọc Nhi"
        },
        {
            "id": "61563440668643",
            "count": 0,
            "name": "Trần Tú"
        },
        {
            "id": "61558691518366",
            "count": 0,
            "name": "Người dùng Facebook"
        },
        {
            "id": "100089033040313",
            "count": 0,
            "name": "Nguyễn Đức Toàn"
        },
        {
            "id": "61562501226870",
            "count": 0,
            "name": "Người dùng Facebook"
        },
        {
            "id": "61553643156660",
            "count": 0,
            "name": "Nguyễn Hoàng"
        },
        {
            "id": "61562870807559",
            "count": 0,
            "name": "Người dùng Facebook"
        },
        {
            "id": "100081016996783",
            "count": 0,
            "name": "Phng Nhi"
        },
        {
            "id": "61561992007088",
            "count": 0,
            "name": "Ngu Ngu Ngu Ngu"
        },
        {
            "id": "100085073240621",
            "count": 0,
            "name": "Dang Gia Khanh"
        },
        {
            "id": "61556666968083",
            "count": 1,
            "name": "Bố Là Gkhanh"
        },
        {
            "id": "61561362279600",
            "count": 0,
            "name": "Rozjx Virky"
        },
        {
            "id": "61553948224884",
            "count": 0,
            "name": "Duck no sad"
        },
        {
            "id": "100035234417533",
            "count": 0,
            "name": "NGUYỄN HỮU ĐỨC"
        },
        {
            "id": "100003133525251",
            "count": 0,
            "name": "Anh Cte Nhất Meta"
        },
        {
            "id": "61563600270027",
            "count": 0,
            "name": "aaaaaaaaaaaaaaaaaaaaaaaaaaaaaaaaaaaaaaaaaaaaaaaaaaaaaaaaaaaaaaaaaaaaaaaaaaa"
        },
        {
            "id": "61563195821713",
            "count": 0,
            "name": "Người dùng Facebook"
        },
        {
            "id": "61563510337368",
            "count": 0,
            "name": "Xin Chào Bot"
        },
        {
            "id": "100055304494389",
            "count": 0,
            "name": "ফেইটান পৰ্টৰ"
        },
        {
            "id": "61563549853253",
            "count": 0,
            "name": "Thu Dũng"
        },
        {
            "id": "61560261936624",
            "count": 0,
            "name": "Nguyễn Nam"
        }
    ],
    "time": 3,
    "last": {
        "time": 3,
        "day": [
            {
                "id": "61554221352772",
                "count": 0,
                "name": "Hoàng Thiên"
            },
            {
                "id": "100075302427263",
                "count": 0,
                "name": "Nguyen Huyen My"
            },
            {
                "id": "100084035917282",
                "count": 0,
                "name": "Ken Yeuem"
            },
            {
                "id": "100088577864287",
                "count": 0,
                "name": "Như Quỳnh"
            },
            {
                "id": "100089281770842",
                "count": 0,
                "name": "Dương Như"
            },
            {
                "id": "61562779757407",
                "count": 0,
                "name": "Người dùng Facebook"
            },
            {
                "id": "61557543538603",
                "count": 0,
                "name": "Người dùng Facebook"
            },
            {
                "id": "100080759211177",
                "count": 0,
                "name": "Bright Dzai"
            },
            {
                "id": "100038740121428",
                "count": 0,
                "name": "Duy メ"
            },
            {
                "id": "61562261835048",
                "count": 0,
                "name": "Người dùng Facebook"
            },
            {
                "id": "61550962658401",
                "count": 0,
                "name": "Lê Ngọc Khánh Băng"
            },
            {
                "id": "100072439105441",
                "count": 0,
                "name": "Lê Chí"
            },
            {
                "id": "61563477320639",
                "count": 0,
                "name": "Người dùng Facebook"
            },
            {
                "id": "61563450811249",
                "count": 0,
                "name": "Người dùng Facebook"
            },
            {
                "id": "100046194132744",
                "count": 0,
                "name": "Đặng Thị Hồng Hải"
            },
            {
                "id": "100000264111892",
                "count": 0,
                "name": "Trịnh Duy Toàn 🖕🏻🐕🐈"
            },
            {
                "id": "61560076791853",
                "count": 0,
                "name": "Người dùng Facebook"
            },
            {
                "id": "100090073282948",
                "count": 0,
                "name": "Gia Long"
            },
            {
                "id": "61563370010550",
                "count": 0,
                "name": "࿐ www.defloration.biz ꗈ Có Lẽ Anh Đã Quá Yêu Em ツ Và Rồi Nhận Ra ღ Em Mang Cho Ta Những Đắng Cay Và Có Lẽ Anh Đã Quá Thương Em ꗈ Giờ Còn Hư Vô 噩 Anh Muốn Vùi Chôn Bao Tháng Ngày ༈፨ Em Đã Xa Anh 噩 Vào Trong Một Chiều Mưa Bay Mang Những Yêu Thương Hòa Du Câu Ca Với Mây Quên Hết Đi Bao Ngày ༈፨ Còn Đọng Lại Trong Nơi Tim ღ Anh Biết Những Chân Thành ಠ༅ཹ﴾ Sẽ Không Dành Cho Anh ꗈ www.drporntube.com ࿐"
            },
            {
                "id": "100083174347639",
                "count": 0,
                "name": "Nguyễn Đức Bình✅"
            },
            {
                "id": "100094911711160",
                "count": 0,
                "name": "Ng Viet Hoang"
            },
            {
                "id": "100073420669646",
                "count": 0,
                "name": "Trần Ngọc Phương Linh"
            },
            {
                "id": "100009801367183",
                "count": 0,
                "name": "Quyết Hoàng"
            },
            {
                "id": "61553578030636",
                "count": 0,
                "name": "Nguyễn Trãi"
            },
            {
                "id": "61552707897116",
                "count": 0,
                "name": "ޑޫއޮންގް ތައި ސަންގް އެވެ"
            },
            {
                "id": "61561840845811",
                "count": 0,
                "name": "Người dùng Facebook"
            },
            {
                "id": "61560667599787",
                "count": 0,
                "name": "Hạ Dương"
            },
            {
                "id": "61560179044114",
                "count": 0,
                "name": "Ngọc Nhi"
            },
            {
                "id": "61563440668643",
                "count": 0,
                "name": "Trần Tú"
            },
            {
                "id": "61558691518366",
                "count": 0,
                "name": "Người dùng Facebook"
            },
            {
                "id": "100089033040313",
                "count": 0,
                "name": "Nguyễn Đức Toàn"
            },
            {
                "id": "61562501226870",
                "count": 0,
                "name": "Người dùng Facebook"
            },
            {
                "id": "61553643156660",
                "count": 0,
                "name": "Nguyễn Hoàng"
            },
            {
                "id": "61562870807559",
                "count": 0,
                "name": "Người dùng Facebook"
            },
            {
                "id": "100081016996783",
                "count": 0,
                "name": "Phng Nhi"
            },
            {
                "id": "61561992007088",
                "count": 0,
                "name": "Ngu Ngu Ngu Ngu"
            },
            {
                "id": "100085073240621",
                "count": 0,
                "name": "Dang Gia Khanh"
            },
            {
                "id": "61556666968083",
                "count": 0,
                "name": "Bố Là Gkhanh"
            },
            {
                "id": "61561362279600",
                "count": 0,
                "name": "Rozjx Virky"
            },
            {
                "id": "61553948224884",
                "count": 0,
                "name": "Duck no sad"
            },
            {
                "id": "100035234417533",
                "count": 0,
                "name": "NGUYỄN HỮU ĐỨC"
            },
            {
                "id": "100003133525251",
                "count": 0,
                "name": "Anh Cte Nhất Meta"
            },
            {
                "id": "61563600270027",
                "count": 0,
                "name": "aaaaaaaaaaaaaaaaaaaaaaaaaaaaaaaaaaaaaaaaaaaaaaaaaaaaaaaaaaaaaaaaaaaaaaaaaaa"
            },
            {
                "id": "61563195821713",
                "count": 0,
                "name": "Người dùng Facebook"
            },
            {
                "id": "61563510337368",
                "count": 0,
                "name": "Xin Chào Bot"
            },
            {
                "id": "100055304494389",
                "count": 0,
                "name": "ফেইটান পৰ্টৰ"
            },
            {
                "id": "61563549853253",
                "count": 0,
                "name": "Thu Dũng"
            },
            {
                "id": "61560261936624",
                "count": 0,
                "name": "Nguyễn Nam"
            }
        ],
        "week": [
            {
                "id": "61554221352772",
                "count": 0,
                "name": "Hoàng Thiên"
            },
            {
                "id": "100075302427263",
                "count": 0,
                "name": "Nguyen Huyen My"
            },
            {
                "id": "100084035917282",
                "count": 9,
                "name": "Ken Yeuem"
            },
            {
                "id": "100088577864287",
                "count": 0,
                "name": "Như Quỳnh"
            },
            {
                "id": "100089281770842",
                "count": 64,
                "name": "Dương Như"
            },
            {
                "id": "61562779757407",
                "count": 0,
                "name": "Người dùng Facebook"
            },
            {
                "id": "61557543538603",
                "count": 0,
                "name": "Người dùng Facebook"
            },
            {
                "id": "100080759211177",
                "count": 1,
                "name": "Bright Dzai"
            },
            {
                "id": "100038740121428",
                "count": 2,
                "name": "Duy メ"
            },
            {
                "id": "61562261835048",
                "count": 2,
                "name": "Cá Chà Bặc"
            },
            {
                "id": "61550962658401",
                "count": 25,
                "name": "Lê Ngọc Khánh Băng"
            },
            {
                "id": "100072439105441",
                "count": 12,
                "name": "Lê Chí"
            },
            {
                "id": "61563477320639",
                "count": 0,
                "name": "Người dùng Facebook"
            },
            {
                "id": "61563450811249",
                "count": 76,
                "name": "Facebook user"
            },
            {
                "id": "100046194132744",
                "count": 58,
                "name": "Đặng Thị Hồng Hải"
            },
            {
                "id": "100000264111892",
                "count": 76,
                "name": "Trịnh Duy Toàn 🖕🏻🐕🐈"
            },
            {
                "id": "61560076791853",
                "count": 0,
                "name": "Nguyễn Quang Trí"
            },
            {
                "id": "100090073282948",
                "count": 2,
                "name": "Gia Long"
            },
            {
                "id": "61563370010550",
                "count": 102,
                "name": "࿐ www.defloration.biz ꗈ Có Lẽ Anh Đã Quá Yêu Em ツ Và Rồi Nhận Ra ღ Em Mang Cho Ta Những Đắng Cay Và Có Lẽ Anh Đã Quá Thương Em ꗈ Giờ Còn Hư Vô 噩 Anh Muốn Vùi Chôn Bao Tháng Ngày ༈፨ Em Đã Xa Anh 噩 Vào Trong Một Chiều Mưa Bay Mang Những Yêu Thương Hòa Du Câu Ca Với Mây Quên Hết Đi Bao Ngày ༈፨ Còn Đọng Lại Trong Nơi Tim ღ Anh Biết Những Chân Thành ಠ༅ཹ﴾ Sẽ Không Dành Cho Anh ꗈ www.drporntube.com ࿐"
            },
            {
                "id": "100083174347639",
                "count": 45,
                "name": "Nguyễn Đức Bình✅"
            },
            {
                "id": "100094911711160",
                "count": 11,
                "name": "Ng Viet Hoang"
            },
            {
                "id": "100073420669646",
                "count": 51,
                "name": "Trần Ngọc Phương Linh"
            },
            {
                "id": "100009801367183",
                "count": 21,
                "name": "Quyết Hoàng"
            },
            {
                "id": "61553578030636",
                "count": 96,
                "name": "Nguyễn Trãi"
            },
            {
                "id": "61552707897116",
                "count": 129,
                "name": "ޑޫއޮންގް ތައި ސަންގް އެވެ"
            },
            {
                "id": "61561840845811",
                "count": 0,
                "name": "Người dùng Facebook"
            },
            {
                "id": "61560667599787",
                "count": 0,
                "name": "Hạ Dương"
            },
            {
                "id": "61560179044114",
                "count": 17,
                "name": "Ngọc Nhi"
            },
            {
                "id": "61563440668643",
                "count": 167,
                "name": "Trần Tú"
            },
            {
                "id": "61558691518366",
                "count": 0,
                "name": "Người dùng Facebook"
            },
            {
                "id": "100089033040313",
                "count": 4,
                "name": "Nguyễn Đức Toàn"
            },
            {
                "id": "61562501226870",
                "count": 10,
                "name": "Ngọc Nhi"
            },
            {
                "id": "61553643156660",
                "count": 72,
                "name": "Nguyễn Hoàng"
            },
            {
                "id": "61562870807559",
                "count": 16,
                "name": "Thai Sang"
            },
            {
                "id": "100081016996783",
                "count": 63,
                "name": "Phng Nhi"
            },
            {
                "id": "61561992007088",
                "count": 0,
                "name": "Ngu Ngu Ngu Ngu"
            },
            {
                "id": "100085073240621",
                "count": 24,
                "name": "Dang Gia Khanh"
            },
            {
                "id": "61556666968083",
                "count": 368,
                "name": "Bố Là Gkhanh"
            },
            {
                "id": "61561362279600",
                "count": 22,
                "name": "Rozjx Virky"
            },
            {
                "id": "61553948224884",
                "count": 94,
                "name": "Duck no sad"
            },
            {
                "id": "100035234417533",
                "count": 108,
                "name": "NGUYỄN HỮU ĐỨC"
            },
            {
                "id": "100003133525251",
                "count": 53,
                "name": "Anh Cte Nhất Meta"
            },
            {
                "id": "61563600270027",
                "count": 3,
                "name": "aaaaaaaaaaaaaaaaaaaaaaaaaaaaaaaaaaaaaaaaaaaaaaaaaaaaaaaaaaaaaaaaaaaaaaaaaaa"
            },
            {
                "id": "61563195821713",
                "count": 7,
                "name": "j"
            },
            {
                "id": "61563510337368",
                "count": 58,
                "name": "Xin Chào Bot"
            },
            {
                "id": "100055304494389",
                "count": 0,
                "name": "ফেইটান পৰ্টৰ"
            },
            {
                "id": "61563549853253",
                "count": 7,
                "name": "Thu Dũng"
            },
            {
                "id": "61560261936624",
                "count": 2,
                "name": "Nguyễn Nam"
            }
        ]
    }
}